{
  "id": "boissons_chaudes",
  "category": "Boissons chaudes",
  "pairs": [
    {"word": "café", "imposter": "thé"},
    {"word": "thé", "imposter": "café"},
    {"word": "cappuccino", "imposter": "latte"},
    {"word": "latte", "imposter": "cappuccino"},
    {"word": "espresso", "imposter": "lungo"},
    {"word": "lungo", "imposter": "espresso"},
    {"word": "americano", "imposter": "café filtre"},
    {"word": "café filtre", "imposter": "americano"},
    {"word": "noisette", "imposter": "macchiato"},
    {"word": "macchiato", "imposter": "noisette"},
    {"word": "ristretto", "imposter": "espresso"},
    {"word": "café crème", "imposter": "latte"},
    {"word": "café au lait", "imposter": "café crème"},
    {"word": "chocolat chaud", "imposter": "cacao"},
    {"word": "cacao", "imposter": "chocolat chaud"},
    {"word": "lait chaud", "imposter": "chocolat chaud"},
    {"word": "thé noir", "imposter": "thé vert"},
    {"word": "thé vert", "imposter": "thé blanc"},
    {"word": "thé blanc", "imposter": "thé oolong"},
    {"word": "thé oolong", "imposter": "thé noir"},
    {"word": "thé rouge", "imposter": "rooibos"},
    {"word": "rooibos", "imposter": "thé rouge"},
    {"word": "tisane", "imposter": "infusion"},
    {"word": "infusion", "imposter": "tisane"},
    {"word": "camomille", "imposter": "tilleul"},
    {"word": "tilleul", "imposter": "verveine"},
    {"word": "verveine", "imposter": "menthe"},
    {"word": "menthe chaude", "imposter": "verveine"},
    {"word": "thé à la menthe", "imposter": "menthe chaude"},
    {"word": "chai", "imposter": "thé aux épices"},
    {"word": "thé matcha", "imposter": "thé vert"},
    {"word": "matcha latte", "imposter": "latte"},
    {"word": "café glacé chaud", "imposter": "cold brew"},
    {"word": "café turc", "imposter": "café grec"},
    {"word": "café grec", "imposter": "café turc"},
    {"word": "café irlandais", "imposter": "café viennois"},
    {"word": "café viennois", "imposter": "café irlandais"},
    {"word": "café frappé", "imposter": "café froid"},
    {"word": "malt chaud", "imposter": "chocolat chaud"},
    {"word": "lait de poule chaud", "imposter": "lait chaud"},
    {"word": "bouillon chaud", "imposter": "soupe"},
    {"word": "punch chaud", "imposter": "vin chaud"},
    {"word": "vin chaud", "imposter": "punch chaud"},
    {"word": "grog", "imposter": "vin chaud"},
    {"word": "hydromel chaud", "imposter": "vin chaud"},
    {"word": "genmaicha", "imposter": "thé vert"},
    {"word": "sencha", "imposter": "matcha"},
    {"word": "gyokuro", "imposter": "sencha"},
    {"word": "darjeeling", "imposter": "assam"},
    {"word": "earl grey", "imposter": "english breakfast"}
  ]
}
