{
  "id": "condiments_sauces",
  "category": "Condiments et sauces",
  "pairs": [
    {"word": "ketchup", "word_hint": "Sauce épaisse sucrée-acide à base de tomates concentrées", "imposter": "sauce tomate", "imposter_hint": "Sauce italienne de tomates cuites aux herbes"},
    {"word": "mayonnaise", "word_hint": "Sauce froide onctueuse à base d'huile et jaune d'œuf", "imposter": "aïoli", "imposter_hint": "Mayonnaise provençale très aillée et dorée"},
    {"word": "moutarde", "word_hint": "Condiment piquant jaune à base de graines broyées", "imposter": "raifort", "imposter_hint": "Racine blanche très piquante râpée, proche du wasabi"},
    {"word": "raifort", "word_hint": "Racine blanche très piquante râpée, proche du wasabi", "imposter": "wasabi", "imposter_hint": "Pâte verte japonaise très piquante servie avec sushis"},
    {"word": "wasabi", "word_hint": "Pâte verte japonaise très piquante servie avec sushis", "imposter": "raifort", "imposter_hint": "Racine blanche très piquante râpée, proche du wasabi"},
    {"word": "sauce soja", "word_hint": "Sauce asiatique brune salée fermentée à base de soja", "imposter": "tamari", "imposter_hint": "Sauce soja japonaise sans blé, plus épaisse et foncée"},
    {"word": "tamari", "word_hint": "Sauce soja japonaise sans blé, plus épaisse et foncée", "imposter": "sauce soja", "imposter_hint": "Sauce asiatique brune salée fermentée à base de soja"},
    {"word": "sauce worcestershire", "word_hint": "Sauce anglaise brune complexe avec anchois et épices", "imposter": "sauce pimentée", "imposter_hint": "Sauce liquide très piquante rouge, base de piments"},
    {"word": "tabasco", "word_hint": "Sauce piquante américaine à base de piments rouges vinaigre", "imposter": "sriracha", "imposter_hint": "Sauce piquante asiatique sucrée-pimentée rouge"},
    {"word": "sriracha", "word_hint": "Sauce piquante asiatique sucrée-pimentée rouge", "imposter": "gochujang", "imposter_hint": "Pâte de piment fermentée coréenne, sucrée et umami"},
    {"word": "harissa", "word_hint": "Pâte de piments rouges nord-africaine très piquante", "imposter": "tabasco", "imposter_hint": "Sauce piquante américaine à base de piments rouges vinaigre"},
    {"word": "sauce pimentée", "word_hint": "Sauce liquide très piquante rouge, base de piments", "imposter": "harissa", "imposter_hint": "Pâte de piments rouges nord-africaine très piquante"},
    {"word": "vinaigre balsamique", "word_hint": "Vinaigre noir épais et sucré de Modène, vieilli en fûts", "imposter": "vinaigre de cidre", "imposter_hint": "Vinaigre doux brun fait de pommes fermentées"},
    {"word": "vinaigre de cidre", "word_hint": "Vinaigre doux brun fait de pommes fermentées", "imposter": "vinaigre de vin", "imposter_hint": "Vinaigre rouge ou blanc fait de vin fermenté acide"},
    {"word": "vinaigre blanc", "word_hint": "Vinaigre incolore très acide, utilisé aussi pour nettoyer", "imposter": "vinaigre balsamique", "imposter_hint": "Vinaigre noir épais et sucré de Modène, vieilli en fûts"},
    {"word": "huile d'olive", "word_hint": "Huile verte ou dorée pressée d'olives, parfumée", "imposter": "huile de colza", "imposter_hint": "Huile jaune dorée neutre extraite de la plante colza"},
    {"word": "huile de tournesol", "word_hint": "Huile neutre légère extraite des graines de tournesol", "imposter": "huile d'arachide", "imposter_hint": "Huile de cacahuète neutre pour fritures hautes températures"},
    {"word": "huile de colza", "word_hint": "Huile jaune dorée neutre extraite de la plante colza", "imposter": "huile de lin", "imposter_hint": "Huile de lin très riche en oméga-3, ne se chauffe pas"},
    {"word": "sauce béarnaise", "word_hint": "Sauce chaude émulsionnée à l'estragon, servie avec steak", "imposter": "sauce hollandaise", "imposter_hint": "Sauce chaude onctueuse au beurre et jaune d'œuf"},
    {"word": "sauce hollandaise", "word_hint": "Sauce chaude onctueuse au beurre et jaune d'œuf", "imposter": "sauce béarnaise", "imposter_hint": "Sauce chaude émulsionnée à l'estragon, servie avec steak"},
    {"word": "sauce béchamel", "word_hint": "Sauce blanche chaude de beurre, farine et lait", "imposter": "sauce mornay", "imposter_hint": "Béchamel enrichie de fromage râpé fondu dedans"},
    {"word": "sauce mornay", "word_hint": "Béchamel enrichie de fromage râpé fondu dedans", "imposter": "sauce béchamel", "imposter_hint": "Sauce blanche chaude de beurre, farine et lait"},
    {"word": "sauce tomate", "word_hint": "Sauce italienne de tomates cuites aux herbes", "imposter": "coulis de tomate", "imposter_hint": "Sauce de tomates crues ou cuites mixées, très lisse"},
    {"word": "coulis de tomate", "word_hint": "Sauce de tomates crues ou cuites mixées, très lisse", "imposter": "passata", "imposter_hint": "Tomates fraîches passées en purée lisse, non cuite"},
    {"word": "passata", "word_hint": "Tomates fraîches passées en purée lisse, non cuite", "imposter": "sauce tomate", "imposter_hint": "Sauce italienne de tomates cuites aux herbes"},
    {"word": "pesto", "word_hint": "Sauce verte italienne au basilic, pignons et parmesan", "imposter": "tapenade", "imposter_hint": "Purée provençale d'olives noires et câpres"},
    {"word": "tapenade", "word_hint": "Purée provençale d'olives noires et câpres", "imposter": "anchoïade", "imposter_hint": "Sauce provençale aux anchois et ail écrasés"},
    {"word": "hummus", "word_hint": "Purée lisse de pois chiches à l'huile et tahini", "imposter": "guacamole", "imposter_hint": "Purée d'avocats avec citron vert et coriandre"},
    {"word": "guacamole", "word_hint": "Purée d'avocats avec citron vert et coriandre", "imposter": "salsa", "imposter_hint": "Condiment mexicain de tomates fraîches et piments hachés"},
    {"word": "salsa", "word_hint": "Condiment mexicain de tomates fraîches et piments hachés", "imposter": "pico de gallo", "imposter_hint": "Salsa fraîche mexicaine avec oignons et coriandre en dés"},
    {"word": "aïoli", "word_hint": "Mayonnaise provençale très aillée et dorée", "imposter": "mayonnaise", "imposter_hint": "Sauce froide onctueuse à base d'huile et jaune d'œuf"},
    {"word": "rouille", "word_hint": "Sauce épicée dorée à l'ail servie avec la bouillabaisse", "imposter": "aïoli", "imposter_hint": "Mayonnaise provençale très aillée et dorée"},
    {"word": "sauce tartare", "word_hint": "Mayonnaise aux cornichons, câpres et herbes hachées", "imposter": "sauce cocktail", "imposter_hint": "Sauce rosée sucrée-piquante pour fruits de mer"},
    {"word": "sauce cocktail", "word_hint": "Sauce rosée sucrée-piquante pour fruits de mer", "imposter": "sauce tartare", "imposter_hint": "Mayonnaise aux cornichons, câpres et herbes hachées"},
    {"word": "vinaigrette", "word_hint": "Sauce froide d'huile et vinaigre pour assaisonner les salades", "imposter": "sauce caesar", "imposter_hint": "Sauce crémeuse avec anchois, ail et parmesan pour salades"},
    {"word": "sauce caesar", "word_hint": "Sauce crémeuse avec anchois, ail et parmesan pour salades", "imposter": "vinaigrette", "imposter_hint": "Sauce froide d'huile et vinaigre pour assaisonner les salades"},
    {"word": "sauce barbecue", "word_hint": "Sauce sucrée-fumée américaine pour viandes grillées", "imposter": "sauce fumée", "imposter_hint": "Sauce liquide avec arôme de fumée concentré"},
    {"word": "sauce teriyaki", "word_hint": "Sauce japonaise sucrée-salée pour viandes laquées", "imposter": "sauce hoisin", "imposter_hint": "Sauce chinoise épaisse sucrée à base de soja fermenté"},
    {"word": "sauce hoisin", "word_hint": "Sauce chinoise épaisse sucrée à base de soja fermenté", "imposter": "sauce teriyaki", "imposter_hint": "Sauce japonaise sucrée-salée pour viandes laquées"},
    {"word": "sauce oyster", "word_hint": "Sauce asiatique épaisse sucrée-salée aux huîtres concentrées", "imposter": "sauce XO", "imposter_hint": "Sauce luxueuse de Hong Kong aux fruits de mer séchés"},
    {"word": "sauce fish", "word_hint": "Sauce de poisson fermentée asiatique, très salée et umami", "imposter": "nuoc-mâm", "imposter_hint": "Sauce de poisson fermentée vietnamienne très salée"},
    {"word": "sauce XO", "word_hint": "Sauce luxueuse de Hong Kong aux fruits de mer séchés", "imposter": "sauce aux huîtres", "imposter_hint": "Sauce asiatique épaisse sucrée-salée aux huîtres concentrées"},
    {"word": "miso", "word_hint": "Pâte japonaise fermentée de soja et sel, très umami", "imposter": "doenjang", "imposter_hint": "Pâte de soja fermentée coréenne, plus forte que le miso"},
    {"word": "nuoc-mâm", "word_hint": "Sauce de poisson fermentée vietnamienne très salée", "imposter": "sauce fish", "imposter_hint": "Sauce de poisson fermentée asiatique, très salée et umami"},
    {"word": "gochujang", "word_hint": "Pâte de piment fermentée coréenne, sucrée et umami", "imposter": "doenjang", "imposter_hint": "Pâte de soja fermentée coréenne, plus forte que le miso"},
    {"word": "tahini", "word_hint": "Purée de sésame blanc crémeuse, base du houmous", "imposter": "purée de sésame", "imposter_hint": "Purée de graines de sésame grillées, plus foncée"},
    {"word": "crème de sésame", "word_hint": "Version asiatique de la pâte de sésame grillé", "imposter": "tahini", "imposter_hint": "Purée de sésame blanc crémeuse, base du houmous"},
    {"word": "confiture d'oignons", "word_hint": "Oignons caramélisés longuement dans sucre et vinaigre", "imposter": "chutney", "imposter_hint": "Condiment indien aigre-doux de fruits et épices"},
    {"word": "chutney", "word_hint": "Condiment indien aigre-doux de fruits et épices", "imposter": "relish", "imposter_hint": "Condiment américain de légumes ou fruits hachés marinés"},
    {"word": "relish", "word_hint": "Condiment américain de légumes ou fruits hachés marinés", "imposter": "pickles", "imposter_hint": "Légumes marinés entiers dans le vinaigre, croquants"},
    {"word": "ketchup", "word_hint": "Sauce épaisse sucrée-acide à base de tomates concentrées", "imposter": "coulis de tomate", "imposter_hint": "Sauce de tomates crues ou cuites mixées, très lisse"},
    {"word": "mayonnaise", "word_hint": "Sauce froide onctueuse à base d'huile et jaune d'œuf", "imposter": "sauce tartare", "imposter_hint": "Mayonnaise aux cornichons, câpres et herbes hachées"},
    {"word": "moutarde de Dijon", "word_hint": "Moutarde fine et forte de Dijon, la plus classique", "imposter": "moutarde à l'ancienne", "imposter_hint": "Moutarde avec graines entières visibles, plus douce"},
    {"word": "moutarde à l'ancienne", "word_hint": "Moutarde avec graines entières visibles, plus douce", "imposter": "moutarde de Meaux", "imposter_hint": "Moutarde à grains semi-concassés de la ville de Meaux"},
    {"word": "vinaigre de framboise", "word_hint": "Vinaigre aromatisé aux framboises, légèrement sucré et fruité", "imposter": "vinaigre de xérès", "imposter_hint": "Vinaigre espagnol fait de vin de Xérès, goût complexe"}
  ]
}
