{
  "id": "pieces_maison",
  "category": "Pièces de la maison",
  "pairs": [
    {"word": "salon", "word_hint": "Pièce principale pour se détendre, recevoir et regarder la télé", "imposter": "séjour", "imposter_hint": "Grande pièce de vie qui regroupe salon et salle à manger"},
    {"word": "cuisine", "word_hint": "Pièce équipée d'un four et d'un évier pour préparer les repas", "imposter": "salle à manger", "imposter_hint": "Pièce avec table et chaises pour prendre les repas en famille"},
    {"word": "chambre", "word_hint": "Pièce intime avec lit pour dormir et se reposer", "imposter": "dortoir", "imposter_hint": "Grande pièce avec plusieurs lits pour dormir ensemble en groupe"},
    {"word": "salle de bain", "word_hint": "Pièce avec baignoire ou douche, lavabo et miroir", "imposter": "salle d'eau", "imposter_hint": "Petite salle de bain sans baignoire, juste douche et lavabo"},
    {"word": "couloir", "word_hint": "Long passage étroit qui relie les différentes pièces d'un logement", "imposter": "hall", "imposter_hint": "Espace d'entrée dans un bâtiment ou un appartement"},
    {"word": "garage", "word_hint": "Espace clos attenant à la maison pour garer la voiture", "imposter": "remise", "imposter_hint": "Petit abri de jardin pour ranger outils et matériel de jardinage"},
    {"word": "cave", "word_hint": "Pièce souterraine fraîche pour stocker le vin et les provisions", "imposter": "sous-sol", "imposter_hint": "Niveau de la maison situé en dessous du rez-de-chaussée"},
    {"word": "grenier", "word_hint": "Espace sous les toits pour stocker affaires et meubles anciens", "imposter": "comble", "imposter_hint": "Espace entre le plafond du dernier étage et la toiture"},
    {"word": "terrasse", "word_hint": "Espace extérieur à l'air libre en prolongement de la maison", "imposter": "balcon", "imposter_hint": "Petite plateforme extérieure en saillie avec garde-corps"},
    {"word": "balcon", "word_hint": "Petite plateforme extérieure en saillie avec garde-corps", "imposter": "loggia", "imposter_hint": "Balcon semi-fermé intégré dans la façade d'un immeuble"},
    {"word": "véranda", "word_hint": "Extension vitrée et chauffée collée à la maison, jardin d'hiver", "imposter": "terrasse", "imposter_hint": "Espace extérieur à l'air libre en prolongement de la maison"},
    {"word": "bureau", "word_hint": "Pièce dédiée au travail, à l'informatique et à l'étude", "imposter": "bibliothèque", "imposter_hint": "Pièce ou meuble pour ranger et lire des livres"},
    {"word": "bibliothèque", "word_hint": "Pièce ou meuble pour ranger et lire des livres", "imposter": "bureau", "imposter_hint": "Pièce dédiée au travail, à l'informatique et à l'étude"},
    {"word": "salle de jeux", "word_hint": "Pièce aménagée pour que les enfants jouent en sécurité", "imposter": "chambre d'enfant", "imposter_hint": "Chambre décorée et aménagée spécialement pour un enfant"},
    {"word": "buanderie", "word_hint": "Pièce avec lave-linge et sèche-linge pour faire la lessive", "imposter": "cellier", "imposter_hint": "Pièce fraîche pour stocker provisions, conserves et bouteilles"},
    {"word": "cellier", "word_hint": "Pièce fraîche pour stocker provisions, conserves et bouteilles", "imposter": "cave", "imposter_hint": "Pièce souterraine fraîche pour stocker le vin et les provisions"},
    {"word": "débarras", "word_hint": "Petite pièce ou placard où on range tout ce qui ne sert pas", "imposter": "placard", "imposter_hint": "Espace de rangement encastré dans le mur avec porte"},
    {"word": "vestibule", "word_hint": "Petite pièce d'entrée d'une maison entre la porte et le couloir", "imposter": "entrée", "imposter_hint": "Zone d'accès et de transition à l'entrée d'un logement"},
    {"word": "entrée", "word_hint": "Zone d'accès et de transition à l'entrée d'un logement", "imposter": "hall", "imposter_hint": "Espace d'entrée dans un bâtiment ou un appartement"},
    {"word": "patio", "word_hint": "Cour intérieure à ciel ouvert typique des maisons méditerranéennes", "imposter": "cour", "imposter_hint": "Espace extérieur clôturé à l'arrière ou sur le côté d'une maison"},
    {"word": "cour", "word_hint": "Espace extérieur clôturé à l'arrière ou sur le côté d'une maison", "imposter": "jardin", "imposter_hint": "Espace extérieur arboré ou fleuri autour d'une maison"},
    {"word": "jardin", "word_hint": "Espace extérieur arboré ou fleuri autour d'une maison", "imposter": "cour", "imposter_hint": "Espace extérieur clôturé à l'arrière ou sur le côté d'une maison"},
    {"word": "sous-sol", "word_hint": "Niveau de la maison situé en dessous du rez-de-chaussée", "imposter": "cave", "imposter_hint": "Pièce souterraine fraîche pour stocker le vin et les provisions"},
    {"word": "rez-de-chaussée", "word_hint": "Premier niveau d'un bâtiment au niveau de la rue", "imposter": "premier étage", "imposter_hint": "Niveau d'un bâtiment situé au-dessus du rez-de-chaussée"},
    {"word": "deuxième étage", "word_hint": "Troisième niveau d'un bâtiment à compter du sol", "imposter": "troisième étage", "imposter_hint": "Quatrième niveau d'un bâtiment à compter du sol"},
    {"word": "soupente", "word_hint": "Petit espace sous un escalier ou sous des combles, peu habitable", "imposter": "mezzanine", "imposter_hint": "Niveau intermédiaire suspendu entre deux étages, ouvert"},
    {"word": "mezzanine", "word_hint": "Niveau intermédiaire suspendu entre deux étages, ouvert", "imposter": "entresol", "imposter_hint": "Niveau entre le rez-de-chaussée et le premier étage, demi-étage"},
    {"word": "palier", "word_hint": "Surface plane entre deux volées d'escalier ou devant les portes", "imposter": "couloir", "imposter_hint": "Long passage étroit qui relie les différentes pièces d'un logement"},
    {"word": "escalier", "word_hint": "Suite de marches pour monter et descendre entre les étages", "imposter": "ascenseur", "imposter_hint": "Cabine mécanique qui monte et descend les étages automatiquement"},
    {"word": "ascenseur", "word_hint": "Cabine mécanique qui monte et descend les étages automatiquement", "imposter": "escalier", "imposter_hint": "Suite de marches pour monter et descendre entre les étages"},
    {"word": "dressing", "word_hint": "Pièce dédiée aux vêtements avec rangements ouverts tout autour", "imposter": "penderie", "imposter_hint": "Grand placard où pendent les vêtements sur des cintres"},
    {"word": "penderie", "word_hint": "Grand placard où pendent les vêtements sur des cintres", "imposter": "armoire", "imposter_hint": "Grand meuble fermé pour ranger vêtements avec portes"},
    {"word": "salle de réception", "word_hint": "Grande pièce pour accueillir et recevoir des invités nombreux", "imposter": "salon", "imposter_hint": "Pièce principale pour se détendre, recevoir et regarder la télé"},
    {"word": "chambre d'amis", "word_hint": "Chambre prévue pour accueillir des invités qui dorment", "imposter": "chambre", "imposter_hint": "Pièce intime avec lit pour dormir et se reposer"},
    {"word": "suite", "word_hint": "Chambre de luxe avec salon attenant dans un hôtel ou grande maison", "imposter": "chambre", "imposter_hint": "Pièce intime avec lit pour dormir et se reposer"},
    {"word": "studio", "word_hint": "Logement d'une seule pièce avec coin cuisine et salle de bain", "imposter": "appartement", "imposter_hint": "Logement dans un immeuble avec plusieurs pièces distinctes"},
    {"word": "appartement", "word_hint": "Logement dans un immeuble avec plusieurs pièces distinctes", "imposter": "maison", "imposter_hint": "Habitation individuelle avec jardin et entrée propre"},
    {"word": "loft", "word_hint": "Grand espace ouvert dans un ancien local industriel transformé", "imposter": "studio", "imposter_hint": "Logement d'une seule pièce avec coin cuisine et salle de bain"},
    {"word": "duplex", "word_hint": "Appartement sur deux niveaux reliés par un escalier intérieur", "imposter": "appartement", "imposter_hint": "Logement dans un immeuble avec plusieurs pièces distinctes"},
    {"word": "villa", "word_hint": "Belle maison individuelle avec jardin et parfois piscine", "imposter": "maison", "imposter_hint": "Habitation individuelle avec jardin et entrée propre"},
    {"word": "chalet", "word_hint": "Maison en bois à toit pentu typique des stations de montagne", "imposter": "villa", "imposter_hint": "Belle maison individuelle avec jardin et parfois piscine"},
    {"word": "manoir", "word_hint": "Grande demeure noble à la campagne moins imposante qu'un château", "imposter": "château", "imposter_hint": "Imposant édifice médiéval avec tours, donjons et douves"},
    {"word": "château", "word_hint": "Imposant édifice médiéval avec tours, donjons et douves", "imposter": "manoir", "imposter_hint": "Grande demeure noble à la campagne moins imposante qu'un château"},
    {"word": "ferme", "word_hint": "Exploitation agricole avec étable, granges et terres cultivées", "imposter": "pavillon", "imposter_hint": "Petite maison individuelle en banlieue avec jardin"},
    {"word": "gîte", "word_hint": "Maison rurale aménagée pour la location aux vacanciers", "imposter": "ferme", "imposter_hint": "Exploitation agricole avec étable, granges et terres cultivées"},
    {"word": "piscine intérieure", "word_hint": "Bassin de natation couvert et chauffé à l'intérieur d'une maison", "imposter": "salle de bain", "imposter_hint": "Pièce avec baignoire ou douche, lavabo et miroir"},
    {"word": "sauna", "word_hint": "Cabine en bois chauffée à très haute température pour transpirer", "imposter": "hammam", "imposter_hint": "Bain de vapeur humide d'origine orientale pour se détendre"},
    {"word": "hammam", "word_hint": "Bain de vapeur humide d'origine orientale pour se détendre", "imposter": "sauna", "imposter_hint": "Cabine en bois chauffée à très haute température pour transpirer"},
    {"word": "jacuzzi", "word_hint": "Baignoire à jets d'eau bouillonnants qui massent le corps", "imposter": "baignoire", "imposter_hint": "Cuve en porcelaine pour se baigner dans l'eau chaude"},
    {"word": "salle de sport", "word_hint": "Pièce équipée d'appareils de musculation et de cardio à domicile", "imposter": "gymnase", "imposter_hint": "Grande salle couverte pour pratiquer différents sports"}
  ]
}
