{
  "id": "metiers_manuels",
  "category": "Métiers manuels et artisanat",
  "pairs": [
    {"word": "plombier", "word_hint": "Artisan qui installe et répare les tuyauteries d'eau et les sanitaires", "imposter": "électricien", "imposter_hint": "Artisan qui installe et répare les circuits et installations électriques"},
    {"word": "électricien", "word_hint": "Artisan qui installe et répare les circuits et installations électriques", "imposter": "plombier", "imposter_hint": "Artisan qui installe et répare les tuyauteries d'eau et les sanitaires"},
    {"word": "maçon", "word_hint": "Artisan du bâtiment qui construit les murs et structures en pierres, briques et béton", "imposter": "carreleur", "imposter_hint": "Artisan qui pose les carreaux de faïence sur les murs et sols"},
    {"word": "carreleur", "word_hint": "Artisan qui pose les carreaux de faïence sur les murs et sols", "imposter": "plâtrier", "imposter_hint": "Artisan qui applique le plâtre sur les murs et les cloisons"},
    {"word": "plâtrier", "word_hint": "Artisan qui applique le plâtre sur les murs et réalise des cloisons", "imposter": "peintre en bâtiment", "imposter_hint": "Artisan qui peint et enduit les murs intérieurs et extérieurs des bâtiments"},
    {"word": "charpentier", "word_hint": "Artisan qui construit et assemble les structures en bois des toitures et charpentes", "imposter": "menuisier", "imposter_hint": "Artisan qui fabrique et pose des portes, fenêtres et mobilier en bois"},
    {"word": "menuisier", "word_hint": "Artisan qui fabrique et pose des portes, fenêtres et mobilier en bois", "imposter": "ébéniste", "imposter_hint": "Artisan du bois de haute qualité qui crée des meubles sur mesure en bois noble"},
    {"word": "ébéniste", "word_hint": "Artisan du bois de haute qualité qui crée des meubles sur mesure en bois noble", "imposter": "menuisier", "imposter_hint": "Artisan qui fabrique et pose des portes, fenêtres et mobilier en bois"},
    {"word": "serrurier", "word_hint": "Artisan qui fabrique, installe et répare serrures, verrous et systèmes de fermeture", "imposter": "forgeron", "imposter_hint": "Artisan qui façonne le métal chauffé à rouge en le frappant sur une enclume"},
    {"word": "forgeron", "word_hint": "Artisan qui façonne le métal chauffé à rouge en le frappant sur une enclume", "imposter": "ferronnier", "imposter_hint": "Artisan qui travaille le fer forgé pour créer grilles, portails et rampes décoratives"},
    {"word": "ferronnier", "word_hint": "Artisan qui travaille le fer forgé pour créer grilles, portails et rampes décoratives", "imposter": "forgeron", "imposter_hint": "Artisan qui façonne le métal chauffé à rouge en le frappant sur une enclume"},
    {"word": "soudeur", "word_hint": "Technicien qui assemble des pièces métalliques par fusion à haute température", "imposter": "chaudronnier", "imposter_hint": "Artisan qui façonne des pièces en métal par déformation à froid ou à chaud"},
    {"word": "chaudronnier", "word_hint": "Artisan qui façonne des pièces en métal par déformation à froid ou à chaud", "imposter": "tuyauteur", "imposter_hint": "Technicien industriel qui installe et soude des tuyauteries dans les usines"},
    {"word": "mécanicien", "word_hint": "Professionnel qui entretient et répare les moteurs et mécaniques de véhicules", "imposter": "carrossier", "imposter_hint": "Artisan qui répare la caisse et la carrosserie des voitures accidentées"},
    {"word": "carrossier", "word_hint": "Artisan qui répare la caisse et la carrosserie des voitures accidentées", "imposter": "tôlier", "imposter_hint": "Artisan qui travaille la tôle métallique pour réparer ou créer des structures"},
    {"word": "vitrier", "word_hint": "Artisan qui coupe et pose le verre pour les fenêtres et vitrages", "imposter": "miroitier", "imposter_hint": "Artisan spécialisé dans la fabrication et pose de miroirs et glaces"},
    {"word": "couvreur", "word_hint": "Artisan qui pose et répare les toitures, tuiles, ardoises et couvertures", "imposter": "zingueur", "imposter_hint": "Artisan spécialisé dans la pose de zinc pour les toitures et gouttières"},
    {"word": "zingueur", "word_hint": "Artisan spécialisé dans la pose de zinc pour les toitures et gouttières", "imposter": "couvreur", "imposter_hint": "Artisan qui pose et répare les toitures, tuiles, ardoises et couvertures"},
    {"word": "paysagiste", "word_hint": "Professionnel qui conçoit et aménage des jardins, parcs et espaces verts", "imposter": "jardinier", "imposter_hint": "Artisan qui entretient les jardins en tondant, taillant et plantant"},
    {"word": "jardinier", "word_hint": "Artisan qui entretient les jardins en tondant, taillant et plantant", "imposter": "paysagiste", "imposter_hint": "Professionnel qui conçoit et aménage des jardins, parcs et espaces verts"},
    {"word": "agriculteur", "word_hint": "Professionnel qui cultive la terre et élève des animaux pour produire des aliments", "imposter": "maraîcher", "imposter_hint": "Agriculteur spécialisé dans la culture de légumes et de fruits sur petites surfaces"},
    {"word": "maraîcher", "word_hint": "Agriculteur spécialisé dans la culture de légumes et de fruits sur petites surfaces", "imposter": "horticulteur", "imposter_hint": "Professionnel qui cultive des fleurs, plantes ornementales et arbustes"},
    {"word": "potier", "word_hint": "Artisan qui façonne l'argile à la main ou au tour pour créer des poteries utilitaires", "imposter": "céramiste", "imposter_hint": "Artisan qui crée des œuvres en céramique cuite avec finitions artistiques"},
    {"word": "céramiste", "word_hint": "Artisan qui crée des œuvres en céramique cuite avec finitions artistiques", "imposter": "potier", "imposter_hint": "Artisan qui façonne l'argile à la main ou au tour pour créer des poteries"},
    {"word": "tisseur", "word_hint": "Artisan qui entrelace des fils sur un métier à tisser pour créer des tissus", "imposter": "brodeur", "imposter_hint": "Artisan qui décore des tissus en cousant des motifs avec du fil coloré"},
    {"word": "brodeur", "word_hint": "Artisan qui décore des tissus en cousant des motifs avec du fil coloré à l'aiguille", "imposter": "tricoteur", "imposter_hint": "Artisan qui crée des vêtements et accessoires en entremêlant des fils avec des aiguilles"},
    {"word": "tailleur", "word_hint": "Artisan qui coupe et coud des vêtements sur mesure, surtout des costumes", "imposter": "couturier", "imposter_hint": "Artisan ou créateur qui coud des vêtements à la main, souvent haute couture"},
    {"word": "couturier", "word_hint": "Artisan ou créateur qui coud des vêtements à la main, souvent haute couture", "imposter": "tailleur", "imposter_hint": "Artisan qui coupe et coud des vêtements sur mesure, surtout des costumes"},
    {"word": "bottier", "word_hint": "Artisan qui fabrique des bottes et chaussures sur mesure en cuir à la main", "imposter": "cordonnier", "imposter_hint": "Artisan qui répare et entretient les chaussures en remplaçant semelles et talons"},
    {"word": "cordonnier", "word_hint": "Artisan qui répare et entretient les chaussures en remplaçant semelles et talons", "imposter": "bottier", "imposter_hint": "Artisan qui fabrique des bottes et chaussures sur mesure en cuir à la main"},
    {"word": "sellier", "word_hint": "Artisan qui fabrique les selles, harnais et équipements en cuir pour chevaux", "imposter": "maroquinier", "imposter_hint": "Artisan qui fabrique des articles en cuir de luxe comme sacs et bagages"},
    {"word": "maroquinier", "word_hint": "Artisan qui fabrique des articles en cuir de luxe comme sacs et bagages", "imposter": "sellier", "imposter_hint": "Artisan qui fabrique les selles, harnais et équipements en cuir pour chevaux"},
    {"word": "bijoutier", "word_hint": "Artisan qui crée et vend des bijoux en métal précieux et pierres semi-précieuses", "imposter": "joaillier", "imposter_hint": "Artisan d'élite spécialisé dans les bijoux avec pierres précieuses de grande valeur"},
    {"word": "joaillier", "word_hint": "Artisan d'élite spécialisé dans les bijoux avec pierres précieuses de grande valeur", "imposter": "orfèvre", "imposter_hint": "Artisan qui travaille les métaux précieux comme l'or et l'argent pour objets d'art"},
    {"word": "orfèvre", "word_hint": "Artisan qui travaille les métaux précieux comme l'or et l'argent pour objets d'art", "imposter": "bijoutier", "imposter_hint": "Artisan qui crée et vend des bijoux en métal précieux et pierres semi-précieuses"},
    {"word": "graveur", "word_hint": "Artisan qui incise des motifs dans un métal, bois ou pierre pour reproduire des images", "imposter": "enlumineur", "imposter_hint": "Artisan médiéval qui décore les manuscrits avec des miniatures colorées et or"},
    {"word": "imprimeur", "word_hint": "Professionnel qui imprime livres, affiches et journaux sur des machines industrielles", "imposter": "sérigraphe", "imposter_hint": "Artisan qui imprime des motifs sur tissu ou papier à travers un écran"},
    {"word": "photographe artisan", "word_hint": "Photographe professionnel indépendant avec son propre studio et clientèle", "imposter": "photographe", "imposter_hint": "Personne qui prend des photos de façon professionnelle ou artistique"},
    {"word": "luthier", "word_hint": "Artisan qui fabrique et répare des instruments à cordes comme violons et guitares", "imposter": "ébéniste", "imposter_hint": "Artisan du bois de haute qualité qui crée des meubles sur mesure en bois noble"},
    {"word": "facteur d'orgues", "word_hint": "Artisan très spécialisé qui construit et restaure des grandes orgues à tuyaux", "imposter": "luthier", "imposter_hint": "Artisan qui fabrique et répare des instruments à cordes comme violons et guitares"},
    {"word": "chapelier", "word_hint": "Artisan qui fabrique des chapeaux et couvre-chefs en feutre, paille ou autres matières", "imposter": "modiste", "imposter_hint": "Artisan qui crée des chapeaux de mode féminins très élaborés et décoratifs"},
    {"word": "modiste", "word_hint": "Artisan qui crée des chapeaux de mode féminins très élaborés et décoratifs", "imposter": "chapelier", "imposter_hint": "Artisan qui fabrique des chapeaux et couvre-chefs en feutre, paille ou autres matières"},
    {"word": "gantier", "word_hint": "Artisan qui fabrique des gants en cuir ou tissu sur mesure", "imposter": "maroquinier", "imposter_hint": "Artisan qui fabrique des articles en cuir de luxe comme sacs et bagages"},
    {"word": "glacier", "word_hint": "Artisan qui fabrique des glaces, sorbets et crèmes glacées artisanales", "imposter": "pâtissier", "imposter_hint": "Artisan qui fabrique des pâtisseries, gâteaux et desserts sucrés"},
    {"word": "boulanger", "word_hint": "Artisan qui pétrit et cuit le pain, les baguettes et les viennoiseries chaque matin", "imposter": "pâtissier", "imposter_hint": "Artisan qui fabrique des pâtisseries, gâteaux et desserts sucrés"},
    {"word": "fromager", "word_hint": "Artisan qui fabrique ou affine des fromages dans une cave ou une fromagerie", "imposter": "crémier", "imposter_hint": "Commerçant qui vend des produits laitiers dans une crémerie"},
    {"word": "fumeur de poisson", "word_hint": "Artisan qui fume des poissons comme le saumon pour les conserver et les parfumer", "imposter": "poissonnier", "imposter_hint": "Commerçant qui vend du poisson frais et des fruits de mer dans sa poissonnerie"},
    {"word": "tonnelier", "word_hint": "Artisan qui fabrique des tonneaux et fûts en bois pour la conservation du vin", "imposter": "charron", "imposter_hint": "Artisan qui fabrique et répare les roues et chariots en bois cerclés de fer"},
    {"word": "charron", "word_hint": "Artisan qui fabrique et répare les roues et chariots en bois cerclés de fer", "imposter": "tonnelier", "imposter_hint": "Artisan qui fabrique des tonneaux et fûts en bois pour la conservation du vin"},
    {"word": "cordier", "word_hint": "Artisan qui fabrique des cordes, câbles et filets en fibres naturelles ou synthétiques", "imposter": "sellier", "imposter_hint": "Artisan qui fabrique les selles, harnais et équipements en cuir pour chevaux"}
  ]
}
