{
  "id": "tailles",
  "category": "Tailles et quantités",
  "pairs": [
    {"word": "grand", "imposter": "petit"},
    {"word": "immense", "imposter": "minuscule"},
    {"word": "énorme", "imposter": "infime"},
    {"word": "géant", "imposter": "nain"},
    {"word": "colossal", "imposter": "lilliputien"},
    {"word": "massif", "imposter": "délicat"},
    {"word": "lourd", "imposter": "léger"},
    {"word": "gros", "imposter": "maigre"},
    {"word": "épais", "imposter": "mince"},
    {"word": "large", "imposter": "étroit"},
    {"word": "long", "imposter": "court"},
    {"word": "haut", "imposter": "bas"},
    {"word": "profond", "imposter": "peu profond"},
    {"word": "vaste", "imposter": "exigu"},
    {"word": "spacieux", "imposter": "étroit"},
    {"word": "beaucoup", "imposter": "peu"},
    {"word": "abondant", "imposter": "rare"},
    {"word": "plein", "imposter": "vide"},
    {"word": "maximum", "imposter": "minimum"},
    {"word": "tout", "imposter": "rien"},
    {"word": "nombreux", "imposter": "peu fréquent"},
    {"word": "fréquent", "imposter": "occasionnel"},
    {"word": "suffisant", "imposter": "insuffisant"},
    {"word": "excès", "imposter": "manque"},
    {"word": "surplus", "imposter": "déficit"},
    {"word": "kilogramme", "imposter": "gramme"},
    {"word": "tonne", "imposter": "kilogramme"},
    {"word": "kilomètre", "imposter": "mètre"},
    {"word": "centimètre", "imposter": "millimètre"},
    {"word": "litre", "imposter": "décilitre"},
    {"word": "hectare", "imposter": "mètre carré"},
    {"word": "millier", "imposter": "centaine"},
    {"word": "million", "imposter": "millier"},
    {"word": "milliard", "imposter": "million"},
    {"word": "double", "imposter": "moitié"},
    {"word": "triple", "imposter": "tiers"},
    {"word": "quadruple", "imposter": "quart"},
    {"word": "moitié", "imposter": "tiers"},
    {"word": "pourcentage", "imposter": "proportion"},
    {"word": "majorité", "imposter": "minorité"},
    {"word": "totalité", "imposter": "partie"},
    {"word": "infini", "imposter": "fini"},
    {"word": "micro", "imposter": "macro"},
    {"word": "nano", "imposter": "micro"},
    {"word": "méga", "imposter": "giga"},
    {"word": "giga", "imposter": "tera"},
    {"word": "premier", "imposter": "dernier"},
    {"word": "unique", "imposter": "multiple"},
    {"word": "singulier", "imposter": "pluriel"},
    {"word": "duo", "imposter": "trio"}
  ]
}
